eccd_datasets/__init__.py
eccd_datasets/groceries/__init__.py
eccd_datasets/groceries/images2.parquet
eccd_datasets/groceries/loader.py
eccd_datasets/groceries/test.py
eccd_datasets/groceries/test_list.txt
eccd_datasets/groceries/train_list.txt
eccd_datasets/groceries/val_list.txt
eccd_datasets/lingerie/__init__.py
eccd_datasets/lingerie/ae_com.parquet
eccd_datasets/lingerie/amazon_com.parquet
eccd_datasets/lingerie/btemptd_com.parquet
eccd_datasets/lingerie/calvinklein_com.parquet
eccd_datasets/lingerie/hankypanky_com.parquet
eccd_datasets/lingerie/loader.py
eccd_datasets/lingerie/macys_com.parquet
eccd_datasets/lingerie/shop_nordstrom_com.parquet
eccd_datasets/lingerie/us_topshop_com.parquet
eccd_datasets/lingerie/victoriassecret_com.parquet
eccd_datasets/m5/__init__.py
eccd_datasets/m5/calendar.parquet
eccd_datasets/m5/loader.py
eccd_datasets/m5/sales.parquet
eccd_datasets/m5/sell_prices.parquet
eccd_datasets/mercari/__init__.py
eccd_datasets/mercari/loader.py
eccd_datasets/mercari/mercari.parquet
eccd_datasets-0.1.1.dist-info/METADATA
eccd_datasets-0.1.1.dist-info/WHEEL
eccd_datasets-0.1.1.dist-info/top_level.txt
eccd_datasets-0.1.1.dist-info/RECORD
