Metadata-Version: 2.1
Name: eccd-datasets
Version: 0.1.1
Summary: A collection of useful datasets
Home-page: https://github.com/wimglenn/resources-example
Author: Diego Kiedanski
Author-email: dkiedanski@gmail.com
License: MIT
Project-URL: Issue Tracker, https://github.com/wimglenn/resources-example/issues
Keywords: packaging,resources
Platform: UNKNOWN
Classifier: Intended Audience :: Developers
Classifier: License :: OSI Approved :: MIT License
Classifier: Operating System :: OS Independent
Classifier: Programming Language :: Python :: 2
Classifier: Programming Language :: Python :: 3
Classifier: Topic :: Software Development :: Libraries :: Python Modules
Classifier: Topic :: System :: Archiving :: Packaging
Classifier: Topic :: System :: Systems Administration
Classifier: Topic :: Utilities
Requires-Dist: setuptools
Requires-Dist: importlib-resources
Requires-Dist: pandas
Requires-Dist: pyarrow
